d_ff/d_ff.vhd
-- d_ff.vhd

library ieee;
use ieee.std_logic_1164.all;
use ieee.numeric_std.all;

entity d_ff is
  port (
    D : in std_logic;
    CLK : in std_logic;
    Q, Q_not : out std_logic
  );
end entity d_ff;

architecture behavioral of d_ff is
  -- internal signals
  signal q_internal : std_logic := '0';
begin
  -- architecture body
  process(CLK)
  begin
    if rising_edge(CLK) then
      -- d flip flop behavior
      if (D = '0') then
        q_internal <= '0';
      elsif (D = '1') then
        q_internal <= '1';
      end if;
    end if;
  end process;

  -- assign signal to outputs
  Q <= q_internal;
  Q_not <= q_internal;


end architecture behavioral;

d_ff/d_ff_tb.vhd
-- d_ff_tb.vhd

library ieee;
use ieee.std_logic_1164.all;
use ieee.numeric_std.all;

entity d_ff_tb is
end entity d_ff_tb;

architecture sim of d_ff_tb is
    -- test bench signals
  signal D, CLK, Q, Q_not : std_logic;

begin
  uut: entity work.d_ff(behavioral)
    port map(
      D => D,
      CLK => CLK,
      Q => Q,
      Q_not => Q_not
    );

  clock_process: process
  begin
    CLK <= '0';
    wait for 10 ns;
    CLK <= '1';
    wait for 10 ns;
  end process;

  stimulus: process
  begin
    D <= '0'; wait for 20 ns;
    D <= '1'; wait for 20 ns;
    D <= '0'; wait for 20 ns;
    D <= '1'; wait for 20 ns;
    D <= '1'; wait for 20 ns;
    D <= '0'; wait for 20 ns;
    D <= '1'; wait for 20 ns;
    D <= '0'; wait for 20 ns;

    wait;
  end process;

end architecture sim;

d_ff/d_ff.vcd
$date
  Tue Apr 21 11:39:29 2026
$end
$version
  GHDL v0
$end
$timescale
  1 fs
$end
$scope module standard $end
$upscope $end
$scope module std_logic_1164 $end
$upscope $end
$scope module numeric_std $end
$upscope $end
$scope module d_ff_tb $end
$var reg 1 ! d $end
$var reg 1 " clk $end
$var reg 1 # q $end
$var reg 1 $ q_not $end
$scope module uut $end
$var reg 1 % d $end
$var reg 1 & clk $end
$var reg 1 ' q $end
$var reg 1 ( q_not $end
$var reg 1 ) q_internal $end
$upscope $end
$upscope $end
$enddefinitions $end
#0
0!
0"
0#
0$
0%
0&
0'
0(
0)
#10000000
1"
1&
#20000000
1!
0"
1%
0&
#30000000
1"
1#
1$
1&
1'
1(
1)
#40000000
0!
0"
0%
0&
#50000000
1"
0#
0$
1&
0'
0(
0)
#60000000
1!
0"
1%
0&
#70000000
1"
1#
1$
1&
1'
1(
1)
#80000000
0"
0&
#90000000
1"
1&
#100000000
0!
0"
0%
0&
#110000000
1"
0#
0$
1&
0'
0(
0)
#120000000
1!
0"
1%
0&
#130000000
1"
1#
1$
1&
1'
1(
1)
#140000000
0!
0"
0%
0&
#150000000
1"
0#
0$
1&
0'
0(
0)
