demux_1x8/demux_1x8.vhd
-- demux_1x8.vhd

library ieee;
use ieee.std_logic_1164.all;
use ieee.numeric_std.all;

entity demux_1x8 is
  port (
    d : in std_logic;
    S : in std_logic_vector(2 downto 0);
    Y : out std_logic_vector(7 downto 0)
  );
end entity demux_1x8;

architecture behavioral of demux_1x8 is
  -- internal signals
begin
  -- architecture body
  process(d, S)
  begin
    Y <= (others => '0'); -- default output to 0
    Y(to_integer(unsigned(S))) <= d;
  end process;
end architecture behavioral;

demux_1x8/demux_1x8_tb.vhd
-- demux_1x8_tb.vhd

library ieee;
use ieee.std_logic_1164.all;
use ieee.numeric_std.all;

entity demux_1x8_tb is
end entity demux_1x8_tb;

architecture sim of demux_1x8_tb is
  -- test bench signals
  signal d : std_logic;
  signal S : std_logic_vector(2 downto 0);
  signal Y : std_logic_vector(7 downto 0);

begin
  uut: entity work.demux_1x8(behavioral)
    port map(
      d => d, S => S, Y => Y
    );

    stimulus: process
    begin
      d <= '0'; S <= "000"; wait for 10 ns;
      d <= '0'; S <= "001"; wait for 10 ns;
      d <= '0'; S <= "010"; wait for 10 ns;
      d <= '0'; S <= "011"; wait for 10 ns;
      d <= '0'; S <= "100"; wait for 10 ns;
      d <= '0'; S <= "101"; wait for 10 ns;
      d <= '0'; S <= "110"; wait for 10 ns;
      d <= '0'; S <= "111"; wait for 10 ns;
      d <= '1'; S <= "000"; wait for 10 ns;
      d <= '1'; S <= "001"; wait for 10 ns;
      d <= '1'; S <= "010"; wait for 10 ns;
      d <= '1'; S <= "011"; wait for 10 ns;
      d <= '1'; S <= "100"; wait for 10 ns;
      d <= '1'; S <= "101"; wait for 10 ns;
      d <= '1'; S <= "110"; wait for 10 ns;
      d <= '1'; S <= "111"; wait for 10 ns; 

      wait;
    end process;

end architecture sim;

demux_1x8/demux_1x8.vcd
$date
  Tue Apr 21 11:26:46 2026
$end
$version
  GHDL v0
$end
$timescale
  1 fs
$end
$scope module standard $end
$upscope $end
$scope module std_logic_1164 $end
$upscope $end
$scope module numeric_std $end
$upscope $end
$scope module demux_1x8_tb $end
$var reg 1 ! d $end
$var reg 3 " s[2:0] $end
$var reg 8 # y[7:0] $end
$scope module uut $end
$var reg 1 $ d $end
$var reg 3 % s[2:0] $end
$var reg 8 & y[7:0] $end
$upscope $end
$upscope $end
$enddefinitions $end
#0
0!
b000 "
b00000000 #
0$
b000 %
b00000000 &
#10000000
b001 "
b001 %
#20000000
b010 "
b010 %
#30000000
b011 "
b011 %
#40000000
b100 "
b100 %
#50000000
b101 "
b101 %
#60000000
b110 "
b110 %
#70000000
b111 "
b111 %
#80000000
1!
b000 "
b00000001 #
1$
b000 %
b00000001 &
#90000000
b001 "
b00000010 #
b001 %
b00000010 &
#100000000
b010 "
b00000100 #
b010 %
b00000100 &
#110000000
b011 "
b00001000 #
b011 %
b00001000 &
#120000000
b100 "
b00010000 #
b100 %
b00010000 &
#130000000
b101 "
b00100000 #
b101 %
b00100000 &
#140000000
b110 "
b01000000 #
b110 %
b01000000 &
#150000000
b111 "
b10000000 #
b111 %
b10000000 &
