mux_2x1/mux_2x1.vhd
-- mux_4x1.vhd

library ieee;
use ieee.std_logic_1164.all;
use ieee.numeric_std.all;

entity mux_2x1 is
  port (
    A : in std_logic_vector(1 downto 0);
    S : in std_logic;
    Y : out std_logic
  );
end entity mux_2x1;

architecture behavioral of mux_2x1 is
  -- internal signals
begin
  -- architecture body
  with S select
    Y <= A(0) when '0',
         A(1) when '1',
         '0' when others;


end architecture behavioral;

mux_2x1/mux_2x1_tb.vhd
-- mux_2x4_tb.vhd

library ieee;
use ieee.std_logic_1164.all;
use ieee.numeric_std.all;

entity mux_2x1_tb is
end entity mux_2x1_tb;

architecture sim of mux_2x1_tb is

  -- test bench signals
  signal A : std_logic_vector(1 downto 0);
  signal S : std_logic;
  signal Y : std_logic;

begin
  uut: entity work.mux_2x1(behavioral)
    port map(
      A => A, S => S, Y => Y
    );

    stimulus: process
    begin
      A <= "00"; S <= '0'; wait for 10 ns;
      A <= "00"; S <= '1'; wait for 10 ns;
      A <= "01"; S <= '0'; wait for 10 ns;
      A <= "01"; S <= '1'; wait for 10 ns;
      A <= "10"; S <= '0'; wait for 10 ns;
      A <= "10"; S <= '1'; wait for 10 ns;
      A <= "11"; S <= '0'; wait for 10 ns;
      A <= "11"; S <= '1'; wait for 10 ns;
      
      wait;
    end process;
end architecture sim;

mux_2x1/mux_2x1.vcd
$date
  Tue Apr 21 08:42:42 2026
$end
$version
  GHDL v0
$end
$timescale
  1 fs
$end
$scope module standard $end
$upscope $end
$scope module std_logic_1164 $end
$upscope $end
$scope module numeric_std $end
$upscope $end
$scope module mux_2x1_tb $end
$var reg 2 ! a[1:0] $end
$var reg 1 " s $end
$var reg 1 # y $end
$scope module uut $end
$var reg 2 $ a[1:0] $end
$var reg 1 % s $end
$var reg 1 & y $end
$upscope $end
$upscope $end
$enddefinitions $end
#0
b00 !
0"
0#
b00 $
0%
0&
#10000000
1"
1%
#20000000
b01 !
0"
1#
b01 $
0%
1&
#30000000
1"
0#
1%
0&
#40000000
b10 !
0"
b10 $
0%
#50000000
1"
1#
1%
1&
#60000000
b11 !
0"
b11 $
0%
#70000000
1"
1%
