bpa_4bit/full_adder.vhd
-- full_adder.vhd

library ieee;
use ieee.std_logic_1164.all;

entity full_adder is
  port(
    A, B, C_IN : in std_logic;
    SUM : out std_logic;
    C_OUT: out std_logic
  );
end full_adder;

-- dataflow style architecture
architecture dataflow of full_adder is
begin
  SUM <= A xor B xor C_IN;
  C_OUT <= (A and B) or (B and C_IN) or (A and C_IN);
end dataflow;

bpa_4bit/bpa_4bit.vhd
-- bpa_4bit.vhd

library ieee;
use ieee.std_logic_1164.all;
use ieee.numeric_std.all;

entity bpa_4bit is
  port (
    A, B : in std_logic_vector(3 downto 0);
    C_IN : in std_logic;
    SUM : out std_logic_vector(3 downto 0);
    C_OUT : out std_logic
  );
end entity bpa_4bit;

architecture structural of bpa_4bit is
  -- component declaration
  component full_adder is
    port(
      A, B, C_IN : in std_logic;
      SUM : out std_logic;
      C_OUT : out std_logic
    );
  end component;

  -- internal carry signals
  signal carry : std_logic_vector(4 downto 0);

begin
  -- architecture body
  carry(0) <= C_IN;

  -- instantiate 4 full adders
  fa0: full_adder port map(
    A => A(0), B => B(0), C_IN => carry(0),
    SUM => SUM(0), C_OUT => carry(1)
  );

  fa1: full_adder port map(
    A => A(1), B => B(1), C_IN => carry(1),
    SUM => SUM(1), C_OUT => carry(2)
  );

  fa2: full_adder port map(
    A => A(2), B => B(2), C_IN => carry(2),
    SUM => SUM(2), C_OUT => carry(3)
  );

  fa3: full_adder port map(
    A => A(3), B => B(3), C_IN => carry(3),
    SUM => SUM(3), C_OUT => carry(4)
  );

  C_OUT <= carry(4);

end structural;

bpa_4bit/bpa_4bit_tb.vhd
-- bpa_4bit_tb.vhd

library ieee;
use ieee.std_logic_1164.all;
use ieee.numeric_std.all;

entity bpa_4bit_tb is
end entity bpa_4bit_tb;

architecture test of bpa_4bit_tb is
  signal A, B, SUM : std_logic_vector(3 downto 0);
  signal C_IN, C_OUT : std_logic;
begin
  uut: entity work.bpa_4bit(structural)
    port map(
      A => A, B => B, C_IN => C_IN,
      SUM => SUM, C_OUT => C_OUT
    );


  stimulus: process
  begin
    -- test with C_IN = 0
    C_IN <= '0';

    A <= "0001"; B <= "0010"; wait for 10 ns; -- 1 + 2 = 3
    A <= "0101"; B <= "1010"; wait for 10 ns; -- 5 + 10 = 15
    A <= "1111"; B <= "0001"; wait for 10 ns; -- 15 + 1 = 0 with carry

    C_IN <= '1';
    A <= "0001"; B <= "0101"; wait for 10 ns; -- 1 + 3 + 1 = 5
    A <= "0011"; B <= "1100"; wait for 10 ns; -- 3 + 12 + 1 = 1 with carry
    
  end process;

end architecture test;

bpa_4bit/bpa_4bit.vcd
$date
  Sat Apr  4 00:03:33 2026
$end
$version
  GHDL v0
$end
$timescale
  1 fs
$end
$scope module standard $end
$upscope $end
$scope module std_logic_1164 $end
$upscope $end
$scope module numeric_std $end
$upscope $end
$scope module bpa_4bit_tb $end
$var reg 4 ! a[3:0] $end
$var reg 4 " b[3:0] $end
$var reg 4 # sum[3:0] $end
$var reg 1 $ c_in $end
$var reg 1 % c_out $end
$scope module uut $end
$var reg 4 & a[3:0] $end
$var reg 4 ' b[3:0] $end
$var reg 1 ( c_in $end
$var reg 4 ) sum[3:0] $end
$var reg 1 * c_out $end
$var reg 5 + carry[4:0] $end
$scope module fa0 $end
$var reg 1 , a $end
$var reg 1 - b $end
$var reg 1 . c_in $end
$var reg 1 / sum $end
$var reg 1 0 c_out $end
$upscope $end
$scope module fa1 $end
$var reg 1 1 a $end
$var reg 1 2 b $end
$var reg 1 3 c_in $end
$var reg 1 4 sum $end
$var reg 1 5 c_out $end
$upscope $end
$scope module fa2 $end
$var reg 1 6 a $end
$var reg 1 7 b $end
$var reg 1 8 c_in $end
$var reg 1 9 sum $end
$var reg 1 : c_out $end
$upscope $end
$scope module fa3 $end
$var reg 1 ; a $end
$var reg 1 < b $end
$var reg 1 = c_in $end
$var reg 1 > sum $end
$var reg 1 ? c_out $end
$upscope $end
$upscope $end
$upscope $end
$enddefinitions $end
#0
b0001 !
b0010 "
b0011 #
0$
0%
b0001 &
b0010 '
0(
b0011 )
0*
b00000 +
1,
0-
0.
1/
00
01
12
03
14
05
06
07
08
09
0:
0;
0<
0=
0>
0?
#10000000
b0101 !
b1010 "
b1111 #
b0101 &
b1010 '
b1111 )
16
19
1<
1>
#20000000
b1111 !
b0001 "
b0000 #
1%
b1111 &
b0001 '
b0000 )
1*
b11110 +
1-
0/
10
11
02
13
04
15
18
09
1:
1;
0<
1=
0>
1?
#30000000
b0001 !
b0101 "
b0111 #
1$
0%
b0001 &
b0101 '
1(
b0111 )
0*
b00011 +
1.
1/
01
14
05
06
17
08
19
0:
0;
0=
0>
0?
#40000000
b0011 !
b1100 "
b0000 #
1%
b0011 &
b1100 '
b0000 )
1*
b11111 +
0-
0/
11
04
15
18
09
1:
1<
1=
0>
1?
#50000000
b0001 !
b0010 "
b0011 #
0$
0%
b0001 &
b0010 '
0(
b0011 )
0*
b00000 +
0.
1/
00
01
12
03
14
05
07
08
09
0:
0<
0=
0>
0?
#60000000
b0101 !
b1010 "
b1111 #
b0101 &
b1010 '
b1111 )
16
19
1<
1>
#70000000
b1111 !
b0001 "
b0000 #
1%
b1111 &
b0001 '
b0000 )
1*
b11110 +
1-
0/
10
11
02
13
04
15
18
09
1:
1;
0<
1=
0>
1?
#80000000
b0001 !
b0101 "
b0111 #
1$
0%
b0001 &
b0101 '
1(
b0111 )
0*
b00011 +
1.
1/
01
14
05
06
17
08
19
0:
0;
0=
0>
0?
#90000000
b0011 !
b1100 "
b0000 #
1%
b0011 &
b1100 '
b0000 )
1*
b11111 +
0-
0/
11
04
15
18
09
1:
1<
1=
0>
1?
#100000000
b0001 !
b0010 "
b0011 #
0$
0%
b0001 &
b0010 '
0(
b0011 )
0*
b00000 +
0.
1/
00
01
12
03
14
05
07
08
09
0:
0<
0=
0>
0?
#110000000
b0101 !
b1010 "
b1111 #
b0101 &
b1010 '
b1111 )
16
19
1<
1>
#120000000
b1111 !
b0001 "
b0000 #
1%
b1111 &
b0001 '
b0000 )
1*
b11110 +
1-
0/
10
11
02
13
04
15
18
09
1:
1;
0<
1=
0>
1?
#130000000
b0001 !
b0101 "
b0111 #
1$
0%
b0001 &
b0101 '
1(
b0111 )
0*
b00011 +
1.
1/
01
14
05
06
17
08
19
0:
0;
0=
0>
0?
#140000000
b0011 !
b1100 "
b0000 #
1%
b0011 &
b1100 '
b0000 )
1*
b11111 +
0-
0/
11
04
15
18
09
1:
1<
1=
0>
1?
#150000000
b0001 !
b0010 "
b0011 #
0$
0%
b0001 &
b0010 '
0(
b0011 )
0*
b00000 +
0.
1/
00
01
12
03
14
05
07
08
09
0:
0<
0=
0>
0?
