seq_detector_1101/seq_detector_1101.vhd
-- seq_detector_1101.vhd

library ieee;
use ieee.std_logic_1164.all;
use ieee.numeric_std.all;

entity seq_detector_1101 is
  port (
    CLK : in std_logic;
    RST : in std_logic;
    d : in std_logic;
    y : out std_logic
  );
end entity seq_detector_1101;

architecture behavioral of seq_detector_1101 is
  -- internal signals
  signal state : integer range 0 to 4 := 0;
begin
  -- architecture body

  process(CLK, RST)
  begin
    if RST = '1' then
      state <= 0;
      y <= '0';
    elsif rising_edge(CLK) then
      -- default output
      y <= '0';

      -- state machine
      case state is
        when 0 =>
          if d = '1' then 
            state <= 1;
          else
            state <= 0;
          end if;

        when 1 =>
          if d = '1' then
            state <= 2;
          else
            state <= 0;
          end if;

        when 2 =>
          if d = '0' then
            state <= 3;
          else
            state <= 0;
          end if;

        when 3 =>
          if d = '1' then
            state <= 4;
            y <= '1';
          else
            state <= 0;
          end if;

        when 4 =>
          if d = '0' then
            state <= 0;
          else
            state <= 2;
          end if;

        when others =>
          state <= 0;
      end case;
    end if;
  end process;

end architecture behavioral;

seq_detector_1101/seq_detector_1101_tb.vhd
-- seq_detector_1101_tb.vhd

library ieee;
use ieee.std_logic_1164.all;
use ieee.numeric_std.all;

entity seq_detector_1101_tb is
end entity seq_detector_1101_tb;

architecture sim of seq_detector_1101_tb is
  signal CLK, RST, d, y : std_logic;

  type test_array is array (0 to 14) of std_logic;
  constant test_seq : test_array := ('1', '1', '0', '1', '1', '0', '1', '0', '1', '0', '1', '1', '0', '1', '1');

  -- test bench signals
begin
  uut: entity work.seq_detector_1101(behavioral)
  port map(
    CLK => CLK, RST => RST,
    d => d, y => y
  );

  clock_process: process
  begin
    CLK <= '1'; wait for 10 ns;
    CLK <= '0'; wait for 10 ns;
  end process;

  stimulus: process
  begin
    RST <= '1';
    wait for 20 ns;
    RST <= '0';

    for i in 0 to 15 loop
      d <= test_seq(i);
      wait for 20 ns;
    end loop;
  end process;

end architecture sim;

seq_detector_1101/seq_detector_1101.vcd
$date
  Tue Apr 21 10:25:06 2026
$end
$version
  GHDL v0
$end
$timescale
  1 fs
$end
$scope module standard $end
$upscope $end
$scope module std_logic_1164 $end
$upscope $end
$scope module numeric_std $end
$upscope $end
$scope module seq_detector_1101_tb $end
$var reg 1 ! clk $end
$var reg 1 " rst $end
$var reg 1 # d $end
$var reg 1 $ y $end
$scope module uut $end
$var reg 1 % clk $end
$var reg 1 & rst $end
$var reg 1 ' d $end
$var reg 1 ( y $end
$var integer 32 ) state $end
$upscope $end
$upscope $end
$enddefinitions $end
#0
1!
1"
U#
0$
1%
1&
U'
0(
b0 )
#10000000
0!
0%
#20000000
1!
0"
1#
1%
0&
1'
b1 )
#30000000
0!
0%
#40000000
1!
1%
b10 )
#50000000
0!
0%
#60000000
1!
0#
1%
0'
b11 )
#70000000
0!
0%
#80000000
1!
1#
1$
1%
1'
1(
b100 )
#90000000
0!
0%
#100000000
1!
0$
1%
0(
b10 )
#110000000
0!
0%
#120000000
1!
0#
1%
0'
b11 )
#130000000
0!
0%
#140000000
1!
1#
1$
1%
1'
1(
b100 )
#150000000
0!
0%
#160000000
1!
0#
0$
1%
0'
0(
b0 )
#170000000
0!
0%
#180000000
1!
1#
1%
1'
b1 )
#190000000
0!
0%
#200000000
1!
0#
1%
0'
b0 )
#210000000
0!
0%
#220000000
1!
1#
1%
1'
b1 )
#230000000
0!
0%
#240000000
1!
1%
b10 )
#250000000
0!
0%
#260000000
1!
0#
1%
0'
b11 )
#270000000
0!
0%
#280000000
1!
1#
1$
1%
1'
1(
b100 )
#290000000
0!
0%
#300000000
1!
0$
1%
0(
b10 )
