decoder_3x8/decoder_3x8.vhd
-- decoder_3x8.vhd

library ieee;
use ieee.std_logic_1164.all;
use ieee.numeric_std.all;

entity decoder_3x8 is
  port (
    A : in std_logic_vector(2 downto 0);
    Y : out std_logic_vector(7 downto 0)
  );
end entity decoder_3x8;

architecture behavioral of decoder_3x8 is
  -- internal signals
begin
  -- architecture body
  with A select
    Y <= "00000001" when "000",
         "00000010" when "001",
         "00000100" when "010",
         "00001000" when "011",
         "00010000" when "100",
         "00100000" when "101",
         "01000000" when "110",
         "10000000" when "111",
         "00000000" when others;

end architecture behavioral;

decoder_3x8/decoder_3x8_tb.vhd
-- decoder_3x8_tb.vhd

library ieee;
use ieee.std_logic_1164.all;
use ieee.numeric_std.all;

entity decoder_3x8_tb is
end entity decoder_3x8_tb;

architecture sim of decoder_3x8_tb is
  signal A : std_logic_vector(2 downto 0);
  signal Y : std_logic_vector(7 downto 0);

begin
  uut: entity work.decoder_3x8(behavioral)
    port map(
      A => A, Y => Y
    );

    stimulus: process
    begin
      A <= "000"; wait for 10 ns;
      A <= "001"; wait for 10 ns;
      A <= "010"; wait for 10 ns;
      A <= "011"; wait for 10 ns;
      A <= "100"; wait for 10 ns;
      A <= "101"; wait for 10 ns;
      A <= "110"; wait for 10 ns;
      A <= "111"; wait for 10 ns;
      wait for 10 ns;

      wait;
    end process;

end architecture sim;

decoder_3x8/decoder_3x8.vcd
$date
  Tue Apr 21 07:59:22 2026
$end
$version
  GHDL v0
$end
$timescale
  1 fs
$end
$scope module standard $end
$upscope $end
$scope module std_logic_1164 $end
$upscope $end
$scope module numeric_std $end
$upscope $end
$scope module decoder_3x8_tb $end
$var reg 3 ! a[2:0] $end
$var reg 8 " y[7:0] $end
$scope module uut $end
$var reg 3 # a[2:0] $end
$var reg 8 $ y[7:0] $end
$upscope $end
$upscope $end
$enddefinitions $end
#0
b000 !
b00000001 "
b000 #
b00000001 $
#10000000
b001 !
b00000010 "
b001 #
b00000010 $
#20000000
b010 !
b00000100 "
b010 #
b00000100 $
#30000000
b011 !
b00001000 "
b011 #
b00001000 $
#40000000
b100 !
b00010000 "
b100 #
b00010000 $
#50000000
b101 !
b00100000 "
b101 #
b00100000 $
#60000000
b110 !
b01000000 "
b110 #
b01000000 $
#70000000
b111 !
b10000000 "
b111 #
b10000000 $
