ripple_counter/ripple_counter.vhd
-- ripple_counter.vhd

library ieee;
use ieee.std_logic_1164.all;
use ieee.numeric_std.all;

entity ripple_counter is
  port (
    CLK, RST : in std_logic;
    q0 : out std_logic;
    q1 : out std_logic
  );
end entity ripple_counter;

architecture behavioral of ripple_counter is
  -- internal signals
  signal q0_reg : std_logic := '0';
  signal q1_reg : std_logic := '0';

begin
  -- tff0: toggles on every rising edge of clk 
  process(CLK, RST)
  begin
    if rst = '1' then
      q0_reg <= '0';
    elsif rising_edge(clk) then
      q0_reg <= not q0_reg;
    end if;
  end process;

  -- tff1: toggles on falling edge of q0 (ie rising edge of not q0)
  process (q0_reg, RST)
  begin
    if rst = '1' then
      q1_reg <= '0';
    elsif falling_edge(q0_reg) then
      q1_reg <= not q1_reg;
    end if;
  end process;

  q0 <= q0_reg;
  q1 <= q1_reg;

end architecture behavioral;

ripple_counter/ripple_counter_tb.vhd
-- ripple_counter_tb.vhd

library ieee;
use ieee.std_logic_1164.all;
use ieee.numeric_std.all;

entity ripple_counter_tb is
end entity ripple_counter_tb;

architecture sim of ripple_counter_tb is
  -- test bench signals
  component ripple_counter is
    port(
      CLK, RST : in std_logic;
      q0, q1 : out std_logic
    );
  end component;

  signal CLK : std_logic := '0';
  signal RST : std_logic := '1';
  signal q0  : std_logic;
  signal q1  : std_logic;

begin
  CLK <= not CLK after 5 ns;

  uut: ripple_counter port map (
    CLK => CLK, RST => RST, q0 => q0, q1 => q1
  );

  process
  begin
    wait for 20 ns;
    rst <= '0';
    wait for 160 ns;
    assert false report "done" severity note;
    wait;
  end process;
end architecture sim;

ripple_counter/ripple_counter.vcd
$date
  Tue Apr 21 10:03:56 2026
$end
$version
  GHDL v0
$end
$timescale
  1 fs
$end
$scope module standard $end
$upscope $end
$scope module std_logic_1164 $end
$upscope $end
$scope module numeric_std $end
$upscope $end
$scope module ripple_counter_tb $end
$var reg 1 ! clk $end
$var reg 1 " rst $end
$var reg 1 # q0 $end
$var reg 1 $ q1 $end
$scope module uut $end
$var reg 1 % clk $end
$var reg 1 & rst $end
$var reg 1 ' q0 $end
$var reg 1 ( q1 $end
$var reg 1 ) q0_reg $end
$var reg 1 * q1_reg $end
$upscope $end
$upscope $end
$enddefinitions $end
#0
0!
1"
0#
0$
0%
1&
0'
0(
0)
0*
#5000000
1!
1%
#10000000
0!
0%
#15000000
1!
1%
#20000000
0!
0"
0%
0&
#25000000
1!
1#
1%
1'
1)
#30000000
0!
0%
#35000000
1!
0#
1$
1%
0'
1(
0)
1*
#40000000
0!
0%
#45000000
1!
1#
1%
1'
1)
#50000000
0!
0%
#55000000
1!
0#
0$
1%
0'
0(
0)
0*
#60000000
0!
0%
#65000000
1!
1#
1%
1'
1)
#70000000
0!
0%
#75000000
1!
0#
1$
1%
0'
1(
0)
1*
