jk_ff/jk_ff.vhd
-- jk_ff.vhdl

library ieee;
use ieee.std_logic_1164.all;
use ieee.numeric_std.all;

entity jk_ff is
  port (
    J, K : in std_logic; -- inputs (J and K)
    CLK : in std_logic; -- clock input
    Q, Q_not : out std_logic -- complement output
  );
end jk_ff;

architecture behavioral of jk_ff is
  -- internal signals
  signal q_internal : std_logic := '0'; -- internal signal to store state
begin
  -- architecture body
  -- process "wakes up" when CLK changes (edge detection)
  process(CLK)
  begin
  -- check for rising edge of clock
    if rising_edge(CLK) then
      -- jk flip-flop behavior
      if (J = '0' and K = '0') then
        q_internal <= q_internal;
      elsif (J = '0' and K = '1') then
        q_internal <= '0';
      elsif (J = '1' and K = '0') then
        q_internal <= '1';
      else -- j = 1 and k = 1
        q_internal <= not q_internal;
      end if;
    end if;
  end process;

  -- assign internal signal to outputs
  Q <= q_internal;
  Q_not <= not q_internal;

end behavioral;

jk_ff/jk_ff_tb.vhd
-- jk_ff_tb.vhdl

library ieee;
use ieee.std_logic_1164.all;
use ieee.numeric_std.all;

entity jk_ff_tb is
end entity jk_ff_tb;

architecture test of jk_ff_tb is
  -- signal to connect to JK flip flop
  signal J, K, CLK, Q, Q_not : std_logic;

begin
  -- instantiate/connect JK flip flop
  -- using <structural> style i.e. connecting components

  uut: entity work.jk_ff(behavioral)
    port map(
      J => J,
      K => K,
      CLK => CLK,
      Q => Q,
      Q_not => Q_not
    );

  -- clock generation process
  clock_process: process
  begin
    CLK <= '0';
    wait for 10 ns;
    CLK <= '1';
    wait for 10 ns;
  end process;

  -- stimulus process (testing combinations)
  stimulus: process
  begin
    J <= '0'; K <= '0';
    wait for 20 ns;

    J <= '0'; K <= '1';
    wait for 20 ns;

    J <= '1'; K <= '0';
    wait for 20 ns;

    J <= '1'; K <= '1';
    wait for 20 ns;

    J <= '1'; K <= '1';
    wait for 20 ns;

    J <= '0'; K <= '0';
    wait for 20 ns;

  wait;
end process;

end architecture test;

jk_ff/jk_ff.vcd
$date
  Fri Apr  3 23:32:58 2026
$end
$version
  GHDL v0
$end
$timescale
  1 fs
$end
$scope module standard $end
$upscope $end
$scope module std_logic_1164 $end
$upscope $end
$scope module numeric_std $end
$upscope $end
$scope module jk_ff_tb $end
$var reg 1 ! j $end
$var reg 1 " k $end
$var reg 1 # clk $end
$var reg 1 $ q $end
$var reg 1 % q_not $end
$scope module uut $end
$var reg 1 & j $end
$var reg 1 ' k $end
$var reg 1 ( clk $end
$var reg 1 ) q $end
$var reg 1 * q_not $end
$var reg 1 + q_internal $end
$upscope $end
$upscope $end
$enddefinitions $end
#0
0!
0"
0#
0$
1%
0&
0'
0(
0)
1*
0+
#10000000
1#
1(
#20000000
1"
0#
1'
0(
#30000000
1#
1(
#40000000
1!
0"
0#
1&
0'
0(
#50000000
1#
1$
0%
1(
1)
0*
1+
#60000000
1"
0#
1'
0(
#70000000
1#
0$
1%
1(
0)
1*
0+
#80000000
0#
0(
#90000000
1#
1$
0%
1(
1)
0*
1+
#100000000
0!
0"
0#
0&
0'
0(
