traffic_controller/traffic_controller.vhd
-- traffic_controller.vhd

library ieee;
use ieee.std_logic_1164.all;
use ieee.numeric_std.all;

entity traffic_controller is
  port (
    CLK : in std_logic; -- clock input (we'll take 10 ns as 1 second interval)

    -- North-2-south lights
    NS_GREEN, NS_YELLOW, NS_RED : out std_logic;

    -- East-2-west lights
    EW_GREEN, EW_YELLOW, EW_RED : out std_logic
  );
end entity traffic_controller;

architecture behavioral of traffic_controller is
  -- internal signals
  signal counter : integer range 0 to 60 := 0; -- counter for timing
  signal state : integer range 0 to 5 := 0; -- 0: NS_GREEN, 1: NS_YELLOW, 2: NS_RED, 3: EW_GREEN, 4: EW_YELLOW, 5: EW_RED

begin
  -- architecture body

  -- process wake up when CLK changes (edge detection)
  process(CLK)
  begin
    if rising_edge(CLK) then
      -- increment each second
      counter <= counter + 1;

      -- state machine for traffic light
      case state is
        when 0 => -- NS green, ES red (25 second)
          if counter = 25 then
            counter <= 0;
            state <= 1; -- move to NS yellow
          end if;

        when 1 => -- NS yellow, ES red (5 second)
          if counter = 5 then
            counter <= 0;
            state <= 2; -- move to NS red, ES green
          end if;

        when 2 => -- ES green, NS red (25 second)
          if counter = 25 then
            counter <= 0;
            state <= 3; -- move to EW yellow
          end if;

        when 3 => -- EW yellow, NS red (5 second)
          if counter = 5 then
            counter <= 0;
            state <= 0; -- move to NS green
          end if;

        when others =>
          state <= 0;
      end case;
    end if;
  end process;

  process(state) -- assign output signal based on current staate
  begin
    -- default all lights off
    NS_GREEN <= '0'; NS_YELLOW <= '0'; NS_RED <= '0';
    EW_GREEN <= '0'; EW_YELLOW <= '0'; EW_RED <= '0';

    -- then case by case, assign light
    case state is
      when 0 => -- NS green, EW red
        NS_GREEN <= '1';
        EW_RED <= '1';

      when 1 => -- NS yellow, EW red
        NS_YELLOW <= '1';
        EW_RED <= '1';

      when 2 => -- EW green, NS red
        EW_GREEN <= '1';
        NS_RED <= '1';

      when 3 => -- EW yellow, NS red
        NS_RED <= '1';
        EW_YELLOW <= '1';

      when others => -- edge case, like when ambulance comes and we manage state for that
        NS_RED <= '1';
        EW_RED <= '1';
    end case;
  end process;

end architecture behavioral;

traffic_controller/traffic_controller_tb.vhd
-- traffic_controller_tb.vhd

library ieee;
use ieee.std_logic_1164.all;
use ieee.numeric_std.all;

entity traffic_controller_tb is
end entity traffic_controller_tb;

architecture sim of traffic_controller_tb is
  signal CLK : std_logic;
  signal NS_GREEN, NS_YELLOW, NS_RED : std_logic;
  signal EW_GREEN, EW_YELLOW, EW_RED : std_logic;

begin
  uut: entity work.traffic_controller(behavioral)
    port map(
      CLK => CLK,
      NS_GREEN => NS_GREEN, NS_YELLOW => NS_YELLOW, NS_RED => NS_RED,
      EW_GREEN => EW_GREEN, EW_YELLOW => EW_YELLOW, EW_RED => EW_RED
    );

  -- clock generation process, 10 ns = 1 second scaling
  clock_process: process
  begin
    CLK <= '0';
    wait for 5 ns;
    CLK <= '1';
    wait for 5 ns;
  end process;

  -- just run for 1500 ns, logic already present in main hdl.
  stimulus: process
  begin
    wait for 1500 ns;

    wait;
  end process;

end architecture sim;

traffic_controller/traffic_controller.vcd
$date
  Wed Apr 22 08:31:20 2026
$end
$version
  GHDL v0
$end
$timescale
  1 fs
$end
$scope module standard $end
$upscope $end
$scope module std_logic_1164 $end
$upscope $end
$scope module numeric_std $end
$upscope $end
$scope module traffic_controller_tb $end
$var reg 1 ! clk $end
$var reg 1 " ns_green $end
$var reg 1 # ns_yellow $end
$var reg 1 $ ns_red $end
$var reg 1 % ew_green $end
$var reg 1 & ew_yellow $end
$var reg 1 ' ew_red $end
$scope module uut $end
$var reg 1 ( clk $end
$var reg 1 ) ns_green $end
$var reg 1 * ns_yellow $end
$var reg 1 + ns_red $end
$var reg 1 , ew_green $end
$var reg 1 - ew_yellow $end
$var reg 1 . ew_red $end
$var integer 32 / counter $end
$var integer 32 0 state $end
$upscope $end
$upscope $end
$enddefinitions $end
#0
0!
1"
0#
0$
0%
0&
1'
0(
1)
0*
0+
0,
0-
1.
b0 /
b0 0
#5000000
1!
1(
b1 /
#10000000
0!
0(
#15000000
1!
1(
b10 /
#20000000
0!
0(
#25000000
1!
1(
b11 /
#30000000
0!
0(
#35000000
1!
1(
b100 /
#40000000
0!
0(
#45000000
1!
1(
b101 /
#50000000
0!
0(
#55000000
1!
1(
b110 /
#60000000
0!
0(
#65000000
1!
1(
b111 /
#70000000
0!
0(
#75000000
1!
1(
b1000 /
#80000000
0!
0(
#85000000
1!
1(
b1001 /
#90000000
0!
0(
#95000000
1!
1(
b1010 /
#100000000
0!
0(
#105000000
1!
1(
b1011 /
#110000000
0!
0(
#115000000
1!
1(
b1100 /
#120000000
0!
0(
#125000000
1!
1(
b1101 /
#130000000
0!
0(
#135000000
1!
1(
b1110 /
#140000000
0!
0(
#145000000
1!
1(
b1111 /
#150000000
0!
0(
#155000000
1!
1(
b10000 /
#160000000
0!
0(
#165000000
1!
1(
b10001 /
#170000000
0!
0(
#175000000
1!
1(
b10010 /
#180000000
0!
0(
#185000000
1!
1(
b10011 /
#190000000
0!
0(
#195000000
1!
1(
b10100 /
#200000000
0!
0(
#205000000
1!
1(
b10101 /
#210000000
0!
0(
#215000000
1!
1(
b10110 /
#220000000
0!
0(
#225000000
1!
1(
b10111 /
#230000000
0!
0(
#235000000
1!
1(
b11000 /
#240000000
0!
0(
#245000000
1!
1(
b11001 /
#250000000
0!
0(
#255000000
1!
0"
1#
1(
0)
1*
1.
b0 /
b1 0
#260000000
0!
0(
#265000000
1!
1(
b1 /
#270000000
0!
0(
#275000000
1!
1(
b10 /
#280000000
0!
0(
#285000000
1!
1(
b11 /
#290000000
0!
0(
#295000000
1!
1(
b100 /
