traffic_controller/traffic_controller.vhd
-- traffic_controller.vhd

library ieee;
use ieee.std_logic_1164.all;
use ieee.numeric_std.all;

entity traffic_controller is
  port (
    CLK : in std_logic; -- clock input (we'll take 10 ns as 1 second interval)

    -- North-2-south lights
    NS_GREEN, NS_YELLOW, NS_RED : out std_logic;

    -- East-2-west lights
    EW_GREEN, EW_YELLOW, EW_RED : out std_logic
  );
end entity traffic_controller;

architecture behavioral of traffic_controller is
  -- internal signals
  signal counter : integer range 0 to 60 := 0; -- counter for timing
  signal state : integer range 0 to 5 := 0; -- 0: NS_GREEN, 1: NS_YELLOW, 2: NS_RED, 3: EW_GREEN, 4: EW_YELLOW, 5: EW_RED

begin
  -- architecture body

  -- process wake up when CLK changes (edge detection)
  process(CLK)
  begin
    if rising_edge(CLK) then
      -- increment each second
      counter <= counter + 1;

      -- state machine for traffic light
      case state is
        when 0 => -- NS green, ES red (25 second)
          if counter = 25 then
            counter <= 0;
            state <= 1; -- move to NS yellow
          end if;

        when 1 => -- NS yellow, ES red (5 second)
          if counter = 5 then
            counter <= 0;
            state <= 2; -- move to NS red, ES green
          end if;

        when 2 => -- ES green, NS red (25 second)
          if counter = 25 then
            counter <= 0;
            state <= 3; -- move to EW yellow
          end if;

        when 3 => -- EW yellow, NS red (5 second)
          if counter = 5 then
            counter <= 0;
            state <= 0; -- move to NS green
          end if;

        when others =>
          state <= 0;
      end case;
    end if;
  end process;

  process(state) -- assign output signal based on current staate
  begin
    -- default all lights off
    NS_GREEN <= '0'; NS_YELLOW <= '0'; NS_RED <= '0';
    EW_GREEN <= '0'; EW_YELLOW <= '0'; EW_RED <= '0';

    -- then case by case, assign light
    case state is
      when 0 => -- NS green, EW red
        NS_GREEN <= '1';
        EW_RED <= '1';

      when 1 => -- NS yellow, EW red
        NS_YELLOW <= '1';
        EW_RED <= '1';

      when 2 => -- EW green, NS red
        EW_GREEN <= '1';
        NS_RED <= '1';

      when 3 => -- EW yellow, NS red
        NS_RED <= '1';
        EW_RED <= '1';

      when others => -- edge case, like when ambulance comes and we manage state for that
        NS_RED <= '1';
        EW_RED <= '1';
    end case;
  end process;

end architecture behavioral;

traffic_controller/traffic_controller_tb.vhd
-- traffic_controller_tb.vhd

library ieee;
use ieee.std_logic_1164.all;
use ieee.numeric_std.all;

entity traffic_controller_tb is
end entity traffic_controller_tb;

architecture sim of traffic_controller_tb is
  signal CLK : std_logic;
  signal NS_GREEN, NS_YELLOW, NS_RED : std_logic;
  signal EW_GREEN, EW_YELLOW, EW_RED : std_logic;

begin
  uut: entity work.traffic_controller(behavioral)
    port map(
      CLK => CLK,
      NS_GREEN => NS_GREEN, NS_YELLOW => NS_YELLOW, NS_RED => NS_RED,
      EW_GREEN => EW_GREEN, EW_YELLOW => EW_YELLOW, EW_RED => EW_RED
    );

  -- clock generation process, 10 ns = 1 second scaling
  clock_process: process
  begin
    CLK <= '0';
    wait for 5 ns;
    CLK <= '1';
    wait for 5 ns;
  end process;

  -- just run for 1500 ns, logic already present in main hdl.
  stimulus: process
  begin
    wait for 1500 ns;

    wait;
  end process;

end architecture sim;

traffic_controller/traffic_controller.vcd
$date
  Mon Apr 20 19:56:32 2026
$end
$version
  GHDL v0
$end
$timescale
  1 fs
$end
$scope module standard $end
$upscope $end
$scope module std_logic_1164 $end
$upscope $end
$scope module numeric_std $end
$upscope $end
$scope module traffic_controller_tb $end
$var reg 1 ! clk $end
$var reg 1 " ns_green $end
$var reg 1 # ns_yellow $end
$var reg 1 $ ns_red $end
$var reg 1 % ew_green $end
$var reg 1 & ew_yellow $end
$var reg 1 ' ew_red $end
$scope module uut $end
$var reg 1 ( clk $end
$var reg 1 ) ns_green $end
$var reg 1 * ns_yellow $end
$var reg 1 + ns_red $end
$var reg 1 , ew_green $end
$var reg 1 - ew_yellow $end
$var reg 1 . ew_red $end
$var integer 32 / counter $end
$var integer 32 0 state $end
$upscope $end
$upscope $end
$enddefinitions $end
#0
0!
1"
0#
0$
0%
0&
1'
0(
1)
0*
0+
0,
0-
1.
b0 /
b0 0
#5000000
1!
1(
b1 /
#10000000
0!
0(
#15000000
1!
1(
b10 /
#20000000
0!
0(
#25000000
1!
1(
b11 /
#30000000
0!
0(
#35000000
1!
1(
b100 /
#40000000
0!
0(
#45000000
1!
1(
b101 /
#50000000
0!
0(
#55000000
1!
1(
b110 /
#60000000
0!
0(
#65000000
1!
1(
b111 /
#70000000
0!
0(
#75000000
1!
1(
b1000 /
#80000000
0!
0(
#85000000
1!
1(
b1001 /
#90000000
0!
0(
#95000000
1!
1(
b1010 /
#100000000
0!
0(
#105000000
1!
1(
b1011 /
#110000000
0!
0(
#115000000
1!
1(
b1100 /
#120000000
0!
0(
#125000000
1!
1(
b1101 /
#130000000
0!
0(
#135000000
1!
1(
b1110 /
#140000000
0!
0(
#145000000
1!
1(
b1111 /
#150000000
0!
0(
#155000000
1!
1(
b10000 /
#160000000
0!
0(
#165000000
1!
1(
b10001 /
#170000000
0!
0(
#175000000
1!
1(
b10010 /
#180000000
0!
0(
#185000000
1!
1(
b10011 /
#190000000
0!
0(
#195000000
1!
1(
b10100 /
#200000000
0!
0(
#205000000
1!
1(
b10101 /
#210000000
0!
0(
#215000000
1!
1(
b10110 /
#220000000
0!
0(
#225000000
1!
1(
b10111 /
#230000000
0!
0(
#235000000
1!
1(
b11000 /
#240000000
0!
0(
#245000000
1!
1(
b11001 /
#250000000
0!
0(
#255000000
1!
0"
1#
1(
0)
1*
1.
b0 /
b1 0
#260000000
0!
0(
#265000000
1!
1(
b1 /
#270000000
0!
0(
#275000000
1!
1(
b10 /
#280000000
0!
0(
#285000000
1!
1(
b11 /
#290000000
0!
0(
#295000000
1!
1(
b100 /
#300000000
0!
0(
#305000000
1!
1(
b101 /
#310000000
0!
0(
#315000000
1!
0#
1$
1%
0'
1(
0*
1+
1,
0.
b0 /
b10 0
#320000000
0!
0(
#325000000
1!
1(
b1 /
#330000000
0!
0(
#335000000
1!
1(
b10 /
#340000000
0!
0(
#345000000
1!
1(
b11 /
#350000000
0!
0(
#355000000
1!
1(
b100 /
#360000000
0!
0(
#365000000
1!
1(
b101 /
#370000000
0!
0(
#375000000
1!
1(
b110 /
#380000000
0!
0(
#385000000
1!
1(
b111 /
#390000000
0!
0(
#395000000
1!
1(
b1000 /
#400000000
0!
0(
#405000000
1!
1(
b1001 /
#410000000
0!
0(
#415000000
1!
1(
b1010 /
#420000000
0!
0(
#425000000
1!
1(
b1011 /
#430000000
0!
0(
#435000000
1!
1(
b1100 /
#440000000
0!
0(
#445000000
1!
1(
b1101 /
#450000000
0!
0(
#455000000
1!
1(
b1110 /
#460000000
0!
0(
#465000000
1!
1(
b1111 /
#470000000
0!
0(
#475000000
1!
1(
b10000 /
#480000000
0!
0(
#485000000
1!
1(
b10001 /
#490000000
0!
0(
#495000000
1!
1(
b10010 /
#500000000
0!
0(
#505000000
1!
1(
b10011 /
#510000000
0!
0(
#515000000
1!
1(
b10100 /
#520000000
0!
0(
#525000000
1!
1(
b10101 /
#530000000
0!
0(
#535000000
1!
1(
b10110 /
#540000000
0!
0(
#545000000
1!
1(
b10111 /
#550000000
0!
0(
#555000000
1!
1(
b11000 /
#560000000
0!
0(
#565000000
1!
1(
b11001 /
#570000000
0!
0(
#575000000
1!
0%
1'
1(
1+
0,
1.
b0 /
b11 0
#580000000
0!
0(
#585000000
1!
1(
b1 /
#590000000
0!
0(
#595000000
1!
1(
b10 /
#600000000
0!
0(
#605000000
1!
1(
b11 /
#610000000
0!
0(
#615000000
1!
1(
b100 /
#620000000
0!
0(
#625000000
1!
1(
b101 /
#630000000
0!
0(
#635000000
1!
1"
0$
1(
1)
0+
1.
b0 /
b0 0
#640000000
0!
0(
#645000000
1!
1(
b1 /
#650000000
0!
0(
#655000000
1!
1(
b10 /
#660000000
0!
0(
#665000000
1!
1(
b11 /
#670000000
0!
0(
#675000000
1!
1(
b100 /
#680000000
0!
0(
#685000000
1!
1(
b101 /
#690000000
0!
0(
#695000000
1!
1(
b110 /
#700000000
0!
0(
#705000000
1!
1(
b111 /
#710000000
0!
0(
#715000000
1!
1(
b1000 /
#720000000
0!
0(
#725000000
1!
1(
b1001 /
#730000000
0!
0(
#735000000
1!
1(
b1010 /
#740000000
0!
0(
#745000000
1!
1(
b1011 /
#750000000
0!
0(
#755000000
1!
1(
b1100 /
#760000000
0!
0(
#765000000
1!
1(
b1101 /
#770000000
0!
0(
#775000000
1!
1(
b1110 /
#780000000
0!
0(
#785000000
1!
1(
b1111 /
#790000000
0!
0(
#795000000
1!
1(
b10000 /
#800000000
0!
0(
#805000000
1!
1(
b10001 /
#810000000
0!
0(
#815000000
1!
1(
b10010 /
#820000000
0!
0(
#825000000
1!
1(
b10011 /
#830000000
0!
0(
#835000000
1!
1(
b10100 /
#840000000
0!
0(
#845000000
1!
1(
b10101 /
#850000000
0!
0(
#855000000
1!
1(
b10110 /
#860000000
0!
0(
#865000000
1!
1(
b10111 /
#870000000
0!
0(
#875000000
1!
1(
b11000 /
#880000000
0!
0(
#885000000
1!
1(
b11001 /
#890000000
0!
0(
#895000000
1!
0"
1#
1(
0)
1*
1.
b0 /
b1 0
#900000000
0!
0(
#905000000
1!
1(
b1 /
#910000000
0!
0(
#915000000
1!
1(
b10 /
#920000000
0!
0(
#925000000
1!
1(
b11 /
#930000000
0!
0(
#935000000
1!
1(
b100 /
#940000000
0!
0(
#945000000
1!
1(
b101 /
#950000000
0!
0(
#955000000
1!
0#
1$
1%
0'
1(
0*
1+
1,
0.
b0 /
b10 0
#960000000
0!
0(
#965000000
1!
1(
b1 /
#970000000
0!
0(
#975000000
1!
1(
b10 /
#980000000
0!
0(
#985000000
1!
1(
b11 /
#990000000
0!
0(
#995000000
1!
1(
b100 /
#1000000000
0!
0(
#1005000000
1!
1(
b101 /
#1010000000
0!
0(
#1015000000
1!
1(
b110 /
#1020000000
0!
0(
#1025000000
1!
1(
b111 /
#1030000000
0!
0(
#1035000000
1!
1(
b1000 /
#1040000000
0!
0(
#1045000000
1!
1(
b1001 /
#1050000000
0!
0(
#1055000000
1!
1(
b1010 /
#1060000000
0!
0(
#1065000000
1!
1(
b1011 /
#1070000000
0!
0(
#1075000000
1!
1(
b1100 /
#1080000000
0!
0(
#1085000000
1!
1(
b1101 /
#1090000000
0!
0(
#1095000000
1!
1(
b1110 /
#1100000000
0!
0(
#1105000000
1!
1(
b1111 /
#1110000000
0!
0(
#1115000000
1!
1(
b10000 /
#1120000000
0!
0(
#1125000000
1!
1(
b10001 /
#1130000000
0!
0(
#1135000000
1!
1(
b10010 /
#1140000000
0!
0(
#1145000000
1!
1(
b10011 /
#1150000000
0!
0(
#1155000000
1!
1(
b10100 /
#1160000000
0!
0(
#1165000000
1!
1(
b10101 /
#1170000000
0!
0(
#1175000000
1!
1(
b10110 /
#1180000000
0!
0(
#1185000000
1!
1(
b10111 /
#1190000000
0!
0(
#1195000000
1!
1(
b11000 /
#1200000000
0!
0(
#1205000000
1!
1(
b11001 /
#1210000000
0!
0(
#1215000000
1!
0%
1'
1(
1+
0,
1.
b0 /
b11 0
#1220000000
0!
0(
#1225000000
1!
1(
b1 /
#1230000000
0!
0(
#1235000000
1!
1(
b10 /
#1240000000
0!
0(
#1245000000
1!
1(
b11 /
#1250000000
0!
0(
#1255000000
1!
1(
b100 /
#1260000000
0!
0(
#1265000000
1!
1(
b101 /
#1270000000
0!
0(
#1275000000
1!
1"
0$
1(
1)
0+
1.
b0 /
b0 0
#1280000000
0!
0(
#1285000000
1!
1(
b1 /
#1290000000
0!
0(
#1295000000
1!
1(
b10 /
#1300000000
0!
0(
#1305000000
1!
1(
b11 /
#1310000000
0!
0(
#1315000000
1!
1(
b100 /
#1320000000
0!
0(
#1325000000
1!
1(
b101 /
#1330000000
0!
0(
#1335000000
1!
1(
b110 /
#1340000000
0!
0(
#1345000000
1!
1(
b111 /
#1350000000
0!
0(
#1355000000
1!
1(
b1000 /
#1360000000
0!
0(
#1365000000
1!
1(
b1001 /
#1370000000
0!
0(
#1375000000
1!
1(
b1010 /
#1380000000
0!
0(
#1385000000
1!
1(
b1011 /
#1390000000
0!
0(
#1395000000
1!
1(
b1100 /
#1400000000
0!
0(
#1405000000
1!
1(
b1101 /
#1410000000
0!
0(
#1415000000
1!
1(
b1110 /
#1420000000
0!
0(
#1425000000
1!
1(
b1111 /
#1430000000
0!
0(
#1435000000
1!
1(
b10000 /
#1440000000
0!
0(
#1445000000
1!
1(
b10001 /
#1450000000
0!
0(
#1455000000
1!
1(
b10010 /
#1460000000
0!
0(
#1465000000
1!
1(
b10011 /
#1470000000
0!
0(
#1475000000
1!
1(
b10100 /
#1480000000
0!
0(
#1485000000
1!
1(
b10101 /
#1490000000
0!
0(
#1495000000
1!
1(
b10110 /
