seq_detector_1011/seq_detector_1011.vhd
-- seq_detector_1011.vhd

library ieee;
use ieee.std_logic_1164.all;
use ieee.numeric_std.all;

entity seq_detector_1011 is
  port (
    CLK: in std_logic;
    RESET_PIN : in std_logic;
    DATA_IN : in std_logic;
    DETECT: out std_logic
  );
end entity seq_detector_1011;

architecture behavioral of seq_detector_1011 is
  -- internal signals

  signal state : integer range 0 to 4 := 0;

  -- definition of states:
  -- 0 = S0, 1 = S1 ...
begin
  -- architecture body

  process(CLK, RESET_PIN)
  begin
    if RESET_PIN = '1' then
      state <= 0;
      DETECT <= '0';

    elsif rising_edge(CLK) then
      -- default output
      DETECT <= '0';

      -- state machine
      case state is
        when 0 =>
          if DATA_IN = '1' then
            state <= 1;
          else
            state <= 0;
          end if;

        when 1 =>
          if DATA_IN = '0' then
            state <= 2;
          else
            state <= 1;
          end if;

        when 2 =>
          if DATA_IN = '1' then
            state <= 3;
          else
            state <= 0;
          end if;

        when 3 =>
          if DATA_IN = '1' then
            state <= 4;
            DETECT <= '1';
          else
            state <= 2;
          end if;

        when 4 =>
          if DATA_IN = '1' then
            state <= 1;
          else
            state <= 2;
          end if;

        when others =>
          state <= 0;
      end case;
    end if;
  end process;

end architecture behavioral;

seq_detector_1011/seq_detector_1011_tb.vhd
-- seq_detector_1011_tb.vhd

library ieee;
use ieee.std_logic_1164.all;
use ieee.numeric_std.all;

entity seq_detector_1011_tb is
end entity seq_detector_1011_tb;

architecture sim of seq_detector_1011_tb is
  -- component declaration
  signal CLK, RESET_PIN, DATA_IN, DETECT : std_logic;

  -- test sequence: 101100101011011
  type test_array is array (0 to 14) of std_logic;
  constant test_seq : test_array := ('1', '0', '1', '1', '0', '0', '1', '0', '1', '0', '1', '1', '0', '1', '1');

begin
  uut: entity work.seq_detector_1011(behavioral)
    port map(
      CLK => CLK, RESET_PIN => RESET_PIN,
      DATA_IN => DATA_IN, DETECT => DETECT
    );

  -- clock generation (100 ns period)
  clock_process: process
  begin
    CLK <= '1'; wait for 50 ns;
    CLK <= '0'; wait for 50 ns;
  end process;

  -- stimulus
  stimulus: process
  begin
    -- reset first
    RESET_PIN <= '1';
    wait for 100 ns;
    RESET_PIN <= '0';

    -- testing the sequence
    for i in 0 to 15 loop
      DATA_IN <= test_seq(i);
      wait for 100 ns;
    end loop;
  end process;

end architecture sim;

seq_detector_1011/seq_detector_1011.vcd
$date
  Mon Apr 20 21:25:03 2026
$end
$version
  GHDL v0
$end
$timescale
  1 fs
$end
$scope module standard $end
$upscope $end
$scope module std_logic_1164 $end
$upscope $end
$scope module numeric_std $end
$upscope $end
$scope module seq_detector_1011_tb $end
$var reg 1 ! clk $end
$var reg 1 " reset_pin $end
$var reg 1 # data_in $end
$var reg 1 $ detect $end
$scope module uut $end
$var reg 1 % clk $end
$var reg 1 & reset_pin $end
$var reg 1 ' data_in $end
$var reg 1 ( detect $end
$var integer 32 ) state $end
$upscope $end
$upscope $end
$enddefinitions $end
#0
1!
1"
U#
0$
1%
1&
U'
0(
b0 )
#50000000
0!
0%
#100000000
1!
0"
1#
1%
0&
1'
b1 )
#150000000
0!
0%
#200000000
1!
0#
1%
0'
b10 )
#250000000
0!
0%
#300000000
1!
1#
1%
1'
b11 )
#350000000
0!
0%
#400000000
1!
1$
1%
1(
b100 )
#450000000
0!
0%
#500000000
1!
0#
0$
1%
0'
0(
b10 )
#550000000
0!
0%
#600000000
1!
1%
b0 )
#650000000
0!
0%
#700000000
1!
1#
1%
1'
b1 )
#750000000
0!
0%
#800000000
1!
0#
1%
0'
b10 )
#850000000
0!
0%
#900000000
1!
1#
1%
1'
b11 )
#950000000
0!
0%
#1000000000
1!
0#
1%
0'
b10 )
#1050000000
0!
0%
#1100000000
1!
1#
1%
1'
b11 )
#1150000000
0!
0%
#1200000000
1!
1$
1%
1(
b100 )
#1250000000
0!
0%
#1300000000
1!
0#
0$
1%
0'
0(
b10 )
#1350000000
0!
0%
#1400000000
1!
1#
1%
1'
b11 )
#1450000000
0!
0%
#1500000000
1!
1$
1%
1(
b100 )
