full_adder/half_adder.vhd
-- half adder.vhd

library ieee;
use ieee.std_logic_1164.all;

entity half_adder is
  port(
    A, B : in std_logic;
    S, C_O: out std_logic
  );
end half_adder;

architecture dataflow of half_adder is
begin
  S <= A xor B;
  C_O <= A and B;
end dataflow;

full_adder/full_adder.vhd
-- full_adder.vhd

library ieee;
use ieee.std_logic_1164.all;
use ieee.numeric_std.all;

entity full_adder is
  port (
    A, B, C_IN: in std_logic;
    SUM, C_OUT: out std_logic
  );
end entity full_adder;

architecture structural of full_adder is
  component half_adder is
    port(
      A, B : in std_logic;
      S, C_O : out std_logic
    );
  end component;

  -- internal carry signals
  signal ha1_sum, ha1_carry : std_logic;
  signal ha2_sum, ha2_carry : std_logic;
begin
  -- instantiate 2 half adders
  ha1: half_adder port map(
    A => A, B => B,
    S => ha1_sum, C_O => ha1_carry
  );

  -- why i'm doing this:
  -- previously i tried to simply assign sum of ha2 as the actual sum, worked
  -- but i tried to map carry of full adder to OR operation of carry of both half adders
  -- this resulted in syntax error, and i found out it wasn't allowed.
  -- so to circumvent, first "store" the output of each half adder in the form of signal
  -- then apply gates to the signals, to get the actual output

  -- tldr: inside port mapping, ONLY mapping is allowed
  -- any other logic, you need additional signal to accomplish

  ha2: half_adder port map(
    A => ha1_sum, B => C_IN,
    S => ha2_sum, C_O => ha2_carry
  );

  -- assigning outputs
  SUM <= ha2_sum;
  C_OUT <= ha1_carry or ha2_carry;

end architecture structural;

full_adder/full_adder_tb.vhd
-- full_adder_tb.vhd

library ieee;
use ieee.std_logic_1164.all;
use ieee.numeric_std.all;

entity full_adder_tb is
end entity full_adder_tb;

architecture sim of full_adder_tb is
  signal A, B, SUM : std_logic;
  signal C_IN, C_OUT : std_logic;
begin
  uut: entity work.full_adder(structural)
    port map(
      A => A, B => B, C_IN => C_IN,
      SUM => SUM, C_OUT => C_OUT
    );

  stimulus: process
  begin
    -- test with C_IN = 0
    C_IN <= '0';
    A <= '0'; B <= '0'; wait for 100 ns;
    A <= '0'; B <= '1'; wait for 100 ns;
    A <= '1'; B <= '0'; wait for 100 ns;
    A <= '1'; B <= '1'; wait for 100 ns;

    -- test with C_IN = 1
    C_IN <= '1';
    A <= '0'; B <= '0'; wait for 100 ns;
    A <= '0'; B <= '1'; wait for 100 ns;
    A <= '1'; B <= '0'; wait for 100 ns;
    A <= '1'; B <= '1'; wait for 100 ns;
  end process;
end architecture sim;

full_adder/full_adder.vcd
$date
  Mon Apr 20 22:16:22 2026
$end
$version
  GHDL v0
$end
$timescale
  1 fs
$end
$scope module standard $end
$upscope $end
$scope module std_logic_1164 $end
$upscope $end
$scope module numeric_std $end
$upscope $end
$scope module full_adder_tb $end
$var reg 1 ! a $end
$var reg 1 " b $end
$var reg 1 # sum $end
$var reg 1 $ c_in $end
$var reg 1 % c_out $end
$scope module uut $end
$var reg 1 & a $end
$var reg 1 ' b $end
$var reg 1 ( c_in $end
$var reg 1 ) sum $end
$var reg 1 * c_out $end
$var reg 1 + ha1_sum $end
$var reg 1 , ha1_carry $end
$var reg 1 - ha2_sum $end
$var reg 1 . ha2_carry $end
$scope module ha1 $end
$var reg 1 / a $end
$var reg 1 0 b $end
$var reg 1 1 s $end
$var reg 1 2 c_o $end
$upscope $end
$scope module ha2 $end
$var reg 1 3 a $end
$var reg 1 4 b $end
$var reg 1 5 s $end
$var reg 1 6 c_o $end
$upscope $end
$upscope $end
$upscope $end
$enddefinitions $end
#0
0!
0"
0#
0$
0%
0&
0'
0(
0)
0*
0+
0,
0-
0.
0/
00
01
02
03
04
05
06
#100000000
1"
1#
1'
1)
1+
1-
10
11
13
15
#200000000
1!
0"
1&
0'
1/
00
#300000000
1"
0#
1%
1'
0)
1*
0+
1,
0-
10
01
12
03
05
#400000000
0!
0"
1#
1$
0%
0&
0'
1(
1)
0*
0,
1-
0/
00
02
14
15
#500000000
1"
0#
1%
1'
0)
1*
1+
0-
1.
10
11
13
05
16
#600000000
1!
0"
1&
0'
1/
00
#700000000
1"
1#
1'
1)
0+
1,
1-
0.
10
01
12
03
15
06
#800000000
0!
0"
0#
0$
0%
0&
0'
0(
0)
0*
0,
0-
0/
00
02
04
05
#900000000
1"
1#
1'
1)
1+
1-
10
11
13
15
#1000000000
1!
0"
1&
0'
1/
00
#1100000000
1"
0#
1%
1'
0)
1*
0+
1,
0-
10
01
12
03
05
#1200000000
0!
0"
1#
1$
0%
0&
0'
1(
1)
0*
0,
1-
0/
00
02
14
15
#1300000000
1"
0#
1%
1'
0)
1*
1+
0-
1.
10
11
13
05
16
#1400000000
1!
0"
1&
0'
1/
00
#1500000000
1"
1#
1'
1)
0+
1,
1-
0.
10
01
12
03
15
06
